{"name":"RVMC Consultants","short_name":"RVMC Consultant","description":"Consultants Services","icons":[{"src":"https:\/\/rvmc.co.in\/wp-content\/uploads\/2021\/10\/Favicon-Logo-512.webp","sizes":"192x192","type":"image\/png","purpose":"any"},{"src":"https:\/\/rvmc.co.in\/wp-content\/uploads\/2021\/10\/Favicon-Logo-512.webp","sizes":"192x192","type":"image\/png","purpose":"maskable"},{"src":"https:\/\/rvmc.co.in\/wp-content\/uploads\/2021\/10\/cropped-Favicon-Logo-512-White.webp","sizes":"512x512","type":"image\/png","purpose":"any"},{"src":"https:\/\/rvmc.co.in\/wp-content\/uploads\/2021\/10\/cropped-Favicon-Logo-512-White.webp","sizes":"512x512","type":"image\/png","purpose":"maskable"}],"background_color":"#ffffff","theme_color":"#ffffff","display":"standalone","orientation":"portrait","start_url":".","scope":"\/"}